MANIFEST.in
README.rst
requirements.txt
setup.py
requirements/base.txt
requirements/repo.txt
requirements/test.txt
src/django_video.egg-info/PKG-INFO
src/django_video.egg-info/SOURCES.txt
src/django_video.egg-info/dependency_links.txt
src/django_video.egg-info/not-zip-safe
src/django_video.egg-info/requires.txt
src/django_video.egg-info/top_level.txt
src/service/__init__.py
src/service/settings.py
src/service/urls.py
src/service/wsgi.py
src/video/__init__.py
src/video/admin.py
src/video/apps.py
src/video/models.py
src/video/tasks.py
src/video/management/__init__.py
src/video/management/commands/__init__.py
src/video/migrations/0001_initial.py
src/video/migrations/0002_auto_20161029_0624.py
src/video/migrations/0003_auto_20161029_0843.py
src/video/migrations/0004_clip_duration.py
src/video/migrations/0005_auto_20161029_1009.py
src/video/migrations/0006_auto_20161101_1349.py
src/video/migrations/0007_video_duration.py
src/video/migrations/0008_auto_20161103_0802.py
src/video/migrations/0009_auto_20161104_1349.py
src/video/migrations/0010_remove_clip_thumbnail.py
src/video/migrations/0011_auto_20161106_0952.py
src/video/migrations/0012_clip_description.py
src/video/migrations/0013_video_dimension.py
src/video/migrations/0014_auto_20170803_1733.py
src/video/migrations/0015_auto_20170916_0210.py
src/video/migrations/0016_auto_20170917_0721.py
src/video/migrations/0017_clip_labels.py
src/video/migrations/0018_auto_20170926_1555.py
src/video/migrations/0019_auto_20170928_0807.py
src/video/migrations/0020_video_url.py
src/video/migrations/0021_auto_20171103_0227.py
src/video/migrations/0022_auto_20171107_0754.py
src/video/migrations/__init__.py
src/video/scripts/__init__.py
src/video/tests/__init__.py
src/video/tests/test_tasks.py